gtf/__init__.py
gtf/base.py
gtf/protect.py
gtf/travis.py
gtf/update.py
gtf/cli/__init__.py
gtf/cli/github_protect_travis.py
gtf/cli/protect.py
gtf/cli/travis.py
gtf/cli/update.py
gtf/files/__init__.py
gtf/files/default-.travis.yml
gtf/files/dm-9847-repo_names.txt
gtf/files/stack-setup.cfg
gtf/tasks/__init__.py
gtf/tasks/sqre.py
gtf/tasks/stack.py
gtf/tasks/test_verbose.py
sqre_gtf-0.1.18.dist-info/DESCRIPTION.rst
sqre_gtf-0.1.18.dist-info/METADATA
sqre_gtf-0.1.18.dist-info/RECORD
sqre_gtf-0.1.18.dist-info/WHEEL
sqre_gtf-0.1.18.dist-info/entry_points.txt
sqre_gtf-0.1.18.dist-info/metadata.json
sqre_gtf-0.1.18.dist-info/top_level.txt
